sqlalchemy_celery_beat/__init__.py
sqlalchemy_celery_beat/__main__.py
sqlalchemy_celery_beat/clockedschedule.py
sqlalchemy_celery_beat/models.py
sqlalchemy_celery_beat/schedulers.py
sqlalchemy_celery_beat/session.py
sqlalchemy_celery_beat/time_utils.py
sqlalchemy_celery_beat/tzcrontab.py
sqlalchemy_celery_beat-0.8.3.dist-info/LICENSE
sqlalchemy_celery_beat-0.8.3.dist-info/METADATA
sqlalchemy_celery_beat-0.8.3.dist-info/WHEEL
sqlalchemy_celery_beat-0.8.3.dist-info/entry_points.txt
sqlalchemy_celery_beat-0.8.3.dist-info/top_level.txt
sqlalchemy_celery_beat-0.8.3.dist-info/RECORD
