Metadata-Version: 2.2
Name: sqlalchemy_celery_beat
Version: 0.8.3
Summary: A Scheduler Based SQLalchemy For Celery
Home-page: https://github.com/farahats9/sqlalchemy-celery-beat
Author: Mohamed Farahat
Author-email: farahats9@yahoo.com
License: MIT
Keywords: celery scheduler sqlalchemy beat
Platform: any
Classifier: Development Status :: 3 - Alpha
Classifier: Intended Audience :: Developers
Classifier: Topic :: Software Development :: Libraries
Classifier: License :: OSI Approved :: MIT License
Classifier: Programming Language :: Python :: 3
Classifier: Programming Language :: Python :: 3.9
License-File: LICENSE
Requires-Dist: celery>=5.0
Requires-Dist: sqlalchemy>=1.4
Requires-Dist: tzdata
Requires-Dist: ephem
Dynamic: author
Dynamic: author-email
Dynamic: classifier
Dynamic: description
Dynamic: description-content-type
Dynamic: home-page
Dynamic: keywords
Dynamic: license
Dynamic: platform
Dynamic: requires-dist
Dynamic: summary
